Nekoriku/__init__.py
Nekoriku/bot.py
Nekoriku/client.py
Nekoriku/colored_logging.py
Nekoriku/embeds.py
Nekoriku/utils.py
Nekoriku/plugins/__init__.py
Nekoriku/plugins/music_event.py
Nekoriku/plugins/music_prefix.py
Nekoriku/plugins/music_slash.py
nekoriku-0.2.4.dist-info/LICENSE
nekoriku-0.2.4.dist-info/METADATA
nekoriku-0.2.4.dist-info/WHEEL
nekoriku-0.2.4.dist-info/top_level.txt
nekoriku-0.2.4.dist-info/RECORD
