Metadata-Version: 2.1
Name: nekoriku
Version: 0.2.4
Summary: แพ็คเกจสำหรับบอทดิสคอร์ดที่มีฟีเจอร์คำสั่งสำหรับเล่นเพลงครบถ้วน
Home-page: https://github.com/NekoSakuraLucia/Nekoriku
Author: NekoSakuraLucia
License: MIT
Requires-Python: >=3.10
License-File: LICENSE
Requires-Dist: discord.py
Requires-Dist: wavelink
Requires-Dist: colorama
